wagtail_taggable/__init__.py
wagtail_taggable/admin.py
wagtail_taggable/apps.py
wagtail_taggable/decorators.py
wagtail_taggable/models.py
wagtail_taggable/static/wagtail_taggable/css/tag-panel.css
wagtail_taggable/templates/wagtail_taggable/tag_chooser.html
wagtail_taggable/templates/wagtail_taggable/tag_wrapper.html
wagtail_taggable/templates/wagtail_taggable/tags_panel.html
wagtail_taggable-0.0.10.dist-info/LICENSE.txt
wagtail_taggable-0.0.10.dist-info/METADATA
wagtail_taggable-0.0.10.dist-info/WHEEL
wagtail_taggable-0.0.10.dist-info/top_level.txt
wagtail_taggable-0.0.10.dist-info/RECORD
