Metadata-Version: 2.1
Name: wagtail-taggable
Version: 0.0.10
Summary: Simple tagging for the Wagtail CMS.
Home-page: https://github.com/octavenz/wagtail-taggable
Author: Claudia Field
Author-email: claudia.field@octave.nz
License: BSD-3-Clause
Classifier: Environment :: Web Environment
Classifier: Framework :: Django
Classifier: Framework :: Wagtail
Classifier: Framework :: Wagtail :: 4
Classifier: Intended Audience :: Developers
Classifier: License :: OSI Approved :: BSD License
Classifier: Programming Language :: Python
Classifier: Programming Language :: Python :: 3
Classifier: Programming Language :: Python :: 3 :: Only
Classifier: Programming Language :: Python :: Implementation :: CPython
Classifier: Topic :: Internet :: WWW/HTTP
Classifier: Topic :: Internet :: WWW/HTTP :: Site Management
Requires-Python: >=3.7
License-File: LICENSE.txt
Requires-Dist: wagtail (>=4.2)
Requires-Dist: wagtail-generic-chooser (>=0.4)
